grokit/__init__.py
grokit/grokit.py
grokit/version.py
grokit/__pycache__/__init__.cpython-312.pyc
grokit/__pycache__/grokit.cpython-312.pyc
grokit/__pycache__/version.cpython-312.pyc
grokit-1.2410.1.dist-info/LICENSE
grokit-1.2410.1.dist-info/METADATA
grokit-1.2410.1.dist-info/WHEEL
grokit-1.2410.1.dist-info/top_level.txt
grokit-1.2410.1.dist-info/RECORD
